LICENSE
MANIFEST.in
README.md
manage.py
requirements.txt
setup.py
hydra_presentation/__init__.py
hydra_presentation/admin.py
hydra_presentation/apps.py
hydra_presentation/models.py
hydra_presentation/polymer.py
hydra_presentation/serializers.py
hydra_presentation/tests.py
hydra_presentation/urls.py
hydra_presentation/version.py
hydra_presentation/views.py
hydra_presentation.egg-info/PKG-INFO
hydra_presentation.egg-info/SOURCES.txt
hydra_presentation.egg-info/dependency_links.txt
hydra_presentation.egg-info/requires.txt
hydra_presentation.egg-info/top_level.txt
hydra_presentation/management/__init__.py
hydra_presentation/management/commands/__init__.py
hydra_presentation/management/commands/polymer.py
hydra_presentation/migrations/__init__.py
hydra_presentation/static/.eslintrc.json
hydra_presentation/static/.gitignore
hydra_presentation/static/LICENSE.md
hydra_presentation/static/README.md
hydra_presentation/static/bower.json
hydra_presentation/static/db.json
hydra_presentation/static/manifest.json
hydra_presentation/static/package.json
hydra_presentation/static/polymer.json
hydra_presentation/static/service-worker.js
hydra_presentation/static/sw-precache-config.js
hydra_presentation/static/.git/HEAD
hydra_presentation/static/.git/ORIG_HEAD
hydra_presentation/static/.git/config
hydra_presentation/static/.git/description
hydra_presentation/static/.git/index
hydra_presentation/static/.git/hooks/README.sample
hydra_presentation/static/.git/info/exclude
hydra_presentation/static/.git/logs/HEAD
hydra_presentation/static/.git/logs/refs/heads/develop
hydra_presentation/static/.git/logs/refs/heads/master
hydra_presentation/static/.git/objects/02/45b75cd24f5801e310ff0241643ebb309b3049
hydra_presentation/static/.git/objects/02/91b969862804d3df0493e3683f4f9d9ebda05e
hydra_presentation/static/.git/objects/05/a8a91087b947b4f12125dd77b7b88d9785c01d
hydra_presentation/static/.git/objects/0b/e304bd71d13666df330c45f98a8421b8803c51
hydra_presentation/static/.git/objects/0b/ef78c4dc44293181472f35ab7c7f99986bd1b3
hydra_presentation/static/.git/objects/11/783692857d617107d6095dbb204745c961a802
hydra_presentation/static/.git/objects/11/c87069d1519d36fd3700d0bd98cf524e88a51d
